statscounter
