Metadata-Version: 1.0
Name: statscounter
Version: 0.0.2
Summary: Python's missing statistical Swiss Army knife
Home-page: https://github.com/datalib/statscounter
Author: Rodrigo Palacios
Author-email: rodrigopala91@gmail.com
License: MIT
Keywords: stats statistics statistic statistical measurements              mean average avg standard deviation std dev stddev              variance Counter StatsCounter collection measurement              measure count sum elements items
Platform: any
